voxel51/__init__.py
voxel51/apps/__init__.py
voxel51/apps/api.py
voxel51/apps/auth.py
voxel51/cli/__init__.py
voxel51/cli/cli.py
voxel51/cli/voxel51
voxel51/constants.py
voxel51/users/__init__.py
voxel51/users/api.py
voxel51/users/auth.py
voxel51/users/jobs.py
voxel51/users/logging.py
voxel51/users/query.py
voxel51/users/utils.py
voxel51/version.json
api_py-0.0.1.dist-info/LICENSE
api_py-0.0.1.dist-info/WHEEL
api_py-0.0.1.dist-info/METADATA
api_py-0.0.1.dist-info/RECORD
